[
    {
        "id": 1,
        "date": "01/09/2023",
        "description": "Compra de supermercado",
        "amount": 245.50,
        "category": "Alimentação"
    },
    {
        "id": 2,
        "date": "03/09/2023",
        "description": "Conta de energia elétrica",
        "amount": 98.75,
        "category": "Utilidades"
    },
    {
        "id": 3,
        "date": "05/09/2023",
        "description": "Serviço de internet",
        "amount": 120.00,
        "category": "Serviços"
    },
    {
        "id": 4,
        "date": "06/09/2023",
        "description": "Compra de roupas",
        "amount": 350.00,
        "category": "Vestuário"
    },
    {
        "id": 5,
        "date": "10/09/2023",
        "description": "Jantar em restaurante",
        "amount": 100.25,
        "category": "Alimentação"
    },
    {
        "id": 6,
        "date": "12/09/2023",
        "description": "Medicamentos",
        "amount": 45.60,
        "category": "Saúde"
    },
    {
        "id": 7,
        "date": "15/09/2023",
        "description": "Academia mensalidade",
        "amount": 89.90,
        "category": "Saúde"
    },
    {
        "id": 8,
        "date": "18/09/2023",
        "description": "Cinema",
        "amount": 36.00,
        "category": "Entretenimento"
    },
    {
        "id": 9,
        "date": "20/09/2023",
        "description": "Gasolina",
        "amount": 150.30,
        "category": "Transporte"
    },
    {
        "id": 10,
        "date": "25/09/2023",
        "description": "Assinatura de streaming",
        "amount": 29.90,
        "category": "Entretenimento"
    }
]